agentsarcadia/__init__.py
agentsarcadia/app.py
agentsarcadia/tool_registry.py
agentsarcadia/tool_router.py
agentsarcadia/nodes/__init__.py
agentsarcadia/nodes/error.py
agentsarcadia/nodes/generic_tool.py
agentsarcadia/nodes/llm_decision.py
agentsarcadia/nodes/parse_response.py
agentsarcadia/nodes/start.py
agentsarcadia/prompts/__init__.py
agentsarcadia/prompts/calculate.py
agentsarcadia/states/__init__.py
agentsarcadia/states/base.py
agentsarcadia/tools/__init__.py
agentsarcadia/tools/add.py
agentsarcadia/tools/compare_num.py
agentsarcadia/tools/divide.py
agentsarcadia/workflows/__init__.py
agentsarcadia/workflows/simple_flow.py
agentsarcadia-0.1.4.dist-info/METADATA
agentsarcadia-0.1.4.dist-info/WHEEL
agentsarcadia-0.1.4.dist-info/top_level.txt
agentsarcadia-0.1.4.dist-info/RECORD
