Metadata-Version: 2.4
Name: agentsarcadia
Version: 0.1.4
Summary: LangGraphによるワークフロー構築を支援するエージェントツール agentsarcadia
Home-page: https://github.com/seiji0906/agentsarcadia
Author: seiji0906
Author-email: yuto.miyashita.info@gmail.com
Classifier: Programming Language :: Python :: 3
Classifier: License :: OSI Approved :: MIT License
Classifier: Operating System :: OS Independent
Requires-Python: >=3.11
Requires-Dist: langchain-openai>=0.3.9
Requires-Dist: langgraph>=0.3.18
Requires-Dist: python-dotenv>=1.0.1
Dynamic: author
Dynamic: author-email
Dynamic: classifier
Dynamic: description
Dynamic: description-content-type
Dynamic: home-page
Dynamic: requires-dist
Dynamic: requires-python
Dynamic: summary
